pyleri/__init__.py
pyleri/choice.py
pyleri/elements.py
pyleri/endofstatement.py
pyleri/exceptions.py
pyleri/expecting.py
pyleri/grammar.py
pyleri/keyword.py
pyleri/list.py
pyleri/node.py
pyleri/optional.py
pyleri/prio.py
pyleri/ref.py
pyleri/regex.py
pyleri/repeat.py
pyleri/result.py
pyleri/rule.py
pyleri/sequence.py
pyleri/this.py
pyleri/token.py
pyleri/tokens.py
pyleri-1.5.0.dist-info/licenses/LICENSE.txt
pyleri-1.5.0.dist-info/METADATA
pyleri-1.5.0.dist-info/WHEEL
pyleri-1.5.0.dist-info/top_level.txt
pyleri-1.5.0.dist-info/RECORD
